{
    "Implicitly requires \u201cvalue\u201d to fit into 128+32=160 bits.": {
        "Id": "HerodotusDev/offchain-evm-headers-processor/abdk_Implicitly_requires_\u201cvalue\u201d_to_fit_into_128+32=160_bits.",
        "Path": "dataset/dataset/cairo/HerodotusDev/offchain-evm-headers-processor/abdk_Implicitly_requires_value_to_fit_into_128_32_160_bits",
        "Project": "https://github.com/HerodotusDev/offchain-evm-headers-processor",
        "Commit": "0xb14e74a5a67bd4882383993036658a57f871e12b",
        "Fix Commit": "af97dae8be5cca025f42da9334596de50762c855",
        "DSL": "Cairo",
        "Vulnerability": "Under-Constrained",
        "Impact": "Soundness",
        "Root Cause": "Missing Input Constraints",
        "Reproduced": false,
        "Location": {
            "Path": "",
            "Function": "",
            "Line": ""
        },
        "Source": {
            "Audit Report": {
                "Source Link": "https://github.com/zksecurity/zkbugs/blob/main/reports/documents/abdk-herodotus.pdf",
                "Bug ID": "Implicitly requires \u201cvalue\u201d to fit into 128+32=160 bits."
            }
        },
        "Commands": {
            "Setup Environment": "",
            "Reproduce": "",
            "Compile and Preprocess": "",
            "Positive Test": "",
            "Find Exploit": "",
            "Clean": ""
        },
        "Short Description of the Vulnerability": "",
        "Short Description of the Exploit": "",
        "Proposed Mitigation": ""
    }
}